<manifest alg="2" build="2017.0.3.363" opt="false" iceEnabled="true" iceMarkupVersion="2" iceEnabledOptions="link,responsive,cachebuster,textStyling" exportTarget="other" domain="estudiomuss.com.ar" resolutions="1x" timestamp="1526950213968">
  <folder name="css">
    <file name="site_global.css" crc="73311052"/>
    <file name="hexa.css" crc="3810811886" ref="hexa"/>
    <file name="nomq_hexa.css" crc="3953915636" ref="hexa"/>
    <file name="index.css" crc="3968984416" ref="index"/>
    <file name="nomq_index.css" crc="4129779097" ref="index"/>
    <file name="boxset.css" crc="207291671" ref="boxset"/>
    <file name="nomq_boxset.css" crc="282459188" ref="boxset"/>
    <file name="saga.css" crc="224715878" ref="saga"/>
    <file name="nomq_saga.css" crc="504440475" ref="saga"/>
    <file name="mesa-alvaro.css" crc="32095830" ref="mesa-alvaro"/>
    <file name="nomq_mesa-alvaro.css" crc="4282515195" ref="mesa-alvaro"/>
    <file name="vaina.css" crc="4159203310" ref="vaina"/>
    <file name="nomq_vaina.css" crc="123633569" ref="vaina"/>
  </folder>
  <folder name="assets">
    <file name="jquery.counterup.min.js" crc="3831897152" seo="true" mt="1385430786000"/>
  </folder>
  <folder name="scripts">
    <file name="jquery-1.8.3.min.js" crc="209076791" ref="index:mesa-alvaro:boxset:hexa:saga:vaina"/>
    <file name="museutils.js" crc="46400467" ref="index:mesa-alvaro:boxset:hexa:saga:vaina"/>
    <file name="whatinput.js" crc="86476730" ref="index:mesa-alvaro:boxset:hexa:saga:vaina"/>
    <file name="museconfig.js" crc="436936948" ref="index:mesa-alvaro:boxset:hexa:saga:vaina"/>
    <file name="webpro.js" crc="4152390327" ref="index"/>
    <file name="musewpslideshow.js" crc="380562115" ref="index"/>
    <file name="jquery.museoverlay.js" crc="3986278607" ref="index"/>
    <file name="touchswipe.js" crc="4228958816" ref="index"/>
    <file name="jquery.musemenu.js" crc="3936200140" ref="index"/>
    <file name="jquery.watch.js" crc="4178585335" ref="index:mesa-alvaro:boxset:hexa:saga:vaina"/>
    <file name="jquery.musepolyfill.bgsize.js" crc="532123423" ref="index:mesa-alvaro:boxset:hexa:saga:vaina"/>
    <file name="musewpdisclosure.js" crc="204784597" ref="index"/>
    <file name="jquery.scrolleffects.js" crc="410690402" ref="index"/>
    <file name="html5shiv.js" crc="4241844378" ref="index:mesa-alvaro:boxset:hexa:saga:vaina"/>
    <file name="jquery.museresponsive.js" crc="52098982" ref="index:mesa-alvaro:boxset:hexa:saga:vaina"/>
    <file name="require.js" crc="85721165" ref="index:mesa-alvaro:boxset:hexa:saga:vaina"/>
  </folder>
  <folder name="images">
    <file name="favicon.ico" crc="500063295" ref="index"/>
    <file name="dsc_0052 copy.jpg" crc="3989009813" seo="true" ref="index">
      <caption webpage="index" alt=""/>
      <caption webpage="index" alt=""/>
      <caption webpage="index" alt=""/>
      <caption webpage="index" alt=""/>
      <caption webpage="index" alt=""/>
    </file>
    <file name="blank.gif" crc="4208392903" ref="index:mesa-alvaro:boxset:hexa:saga:vaina"/>
    <file name="dsc_0102 copy.jpg" crc="268172209" seo="true" ref="index">
      <caption webpage="index" alt=""/>
      <caption webpage="index" alt=""/>
      <caption webpage="index" alt=""/>
      <caption webpage="index" alt=""/>
      <caption webpage="index" alt=""/>
    </file>
    <file name="dsc_0048 copy.jpg" crc="394433884" seo="true" ref="index">
      <caption webpage="index" alt=""/>
      <caption webpage="index" alt=""/>
      <caption webpage="index" alt=""/>
      <caption webpage="index" alt=""/>
      <caption webpage="index" alt=""/>
    </file>
    <file name="flecha-izquierda.png" crc="3975364059" ref="index">
      <caption webpage="index" alt=""/>
      <caption webpage="index" alt=""/>
      <caption webpage="index" alt=""/>
      <caption webpage="index" alt=""/>
      <caption webpage="index" alt=""/>
    </file>
    <file name="flecha-derecha.png" crc="152649081" ref="index">
      <caption webpage="index" alt=""/>
      <caption webpage="index" alt=""/>
      <caption webpage="index" alt=""/>
      <caption webpage="index" alt=""/>
      <caption webpage="index" alt=""/>
    </file>
    <file name="loading.gif" crc="3815509949" ref="index"/>
    <file name="logo blanco.png" crc="4108408676" seo="true" ref="index">
      <caption webpage="index" alt=""/>
      <caption webpage="index" alt=""/>
      <caption webpage="index" alt=""/>
      <caption webpage="index" alt=""/>
      <caption webpage="index" alt=""/>
      <caption webpage="index" alt=""/>
      <caption webpage="index" alt=""/>
      <caption webpage="index" alt=""/>
      <caption webpage="index" alt=""/>
      <caption webpage="index" alt=""/>
      <caption webpage="index" alt=""/>
      <caption webpage="index" alt=""/>
      <caption webpage="index" alt=""/>
      <caption webpage="index" alt=""/>
      <caption webpage="index" alt=""/>
    </file>
    <file name="quienes-somos.png" crc="336959440" ref="index">
      <caption webpage="index" alt=""/>
      <caption webpage="index" alt=""/>
      <caption webpage="index" alt=""/>
      <caption webpage="index" alt=""/>
      <caption webpage="index" alt=""/>
    </file>
    <file name="que-hacemos.png" crc="482448688" ref="index">
      <caption webpage="index" alt=""/>
      <caption webpage="index" alt=""/>
      <caption webpage="index" alt=""/>
      <caption webpage="index" alt=""/>
      <caption webpage="index" alt=""/>
    </file>
    <file name="lapiz mecanico.svg" crc="394900175" ref="index"/>
    <file name="lapiz mecanico_poster_u28558.png" crc="364378103" ref="index"/>
    <file name="di.svg" crc="4058542231" ref="index"/>
    <file name="di_poster_u28550.png" crc="4273496535" ref="index"/>
    <file name="consultoria.svg" crc="3876799544" ref="index"/>
    <file name="consultoria_poster_u28542.png" crc="527136770" ref="index"/>
    <file name="dsc_0027 copy 2.jpg" crc="367827678" ref="index">
      <caption webpage="index" alt=""/>
    </file>
    <file name="boxset_6.jpg" crc="4022776551" ref="index:boxset">
      <caption webpage="index" alt=""/>
      <caption webpage="boxset" alt=""/>
    </file>
    <file name="hexa - (4).png" crc="261373216" ref="index">
      <caption webpage="index" alt=""/>
    </file>
    <file name="saga - portada.jpg" crc="3891955486" ref="index:saga">
      <caption webpage="index" alt=""/>
      <caption webpage="saga" alt=""/>
    </file>
    <file name="vaina_presentacion.jpg" crc="187814034" ref="index:vaina">
      <caption webpage="index" alt=""/>
    </file>
    <file name="u30000-4.png" crc="4174656471" ref="index"/>
    <file name="guido.jpg" crc="463074477" seo="true" ref="index">
      <caption webpage="index" alt="Guido Torres Diseñador Industrial en MUSS"/>
      <caption webpage="index" alt="Guido Torres Diseñador Industrial en MUSS"/>
      <caption webpage="index" alt="Guido Torres Diseñador Industrial en MUSS"/>
      <caption webpage="index" alt="Guido Torres Diseñador Industrial en MUSS"/>
      <caption webpage="index" alt="Guido Torres Diseñador Industrial en MUSS"/>
    </file>
    <file name="joaco.jpg" crc="82775189" seo="true" ref="index">
      <caption webpage="index" alt="Joaquín de Sant' Ana Diseñador Industrial en MUSS"/>
      <caption webpage="index" alt="Joaquín de Sant' Ana Diseñador Industrial en MUSS"/>
      <caption webpage="index" alt="Joaquín de Sant' Ana Diseñador Industrial en MUSS"/>
      <caption webpage="index" alt="Joaquín de Sant' Ana Diseñador Industrial en MUSS"/>
      <caption webpage="index" alt="Joaquín de Sant' Ana Diseñador Industrial en MUSS"/>
    </file>
    <file name="asset-2b.svg" crc="3926745848" seo="true" ref="index">
      <caption webpage="index" alt=""/>
      <caption webpage="index" alt=""/>
      <caption webpage="index" alt=""/>
      <caption webpage="index" alt=""/>
      <caption webpage="index" alt=""/>
    </file>
    <file name="asset 2b_poster_.png" crc="220126826" ref="index"/>
    <file name="asset-3b.svg" crc="495820761" seo="true" ref="index">
      <caption webpage="index" alt=""/>
      <caption webpage="index" alt=""/>
      <caption webpage="index" alt=""/>
      <caption webpage="index" alt=""/>
      <caption webpage="index" alt=""/>
    </file>
    <file name="asset 3b_poster_.png" crc="4215133252" ref="index"/>
    <file name="asset-1b.svg" crc="4052092844" seo="true" ref="index">
      <caption webpage="index" alt=""/>
      <caption webpage="index" alt=""/>
      <caption webpage="index" alt=""/>
      <caption webpage="index" alt=""/>
      <caption webpage="index" alt=""/>
    </file>
    <file name="asset 1b_poster_.png" crc="494638334" ref="index"/>
    <file name="asset 1c.svg" crc="4225326476" ref="index:mesa-alvaro:boxset:hexa:saga:vaina"/>
    <file name="asset 1c_poster_u29298.png" crc="82481991" ref="index:mesa-alvaro:boxset:hexa:saga:vaina"/>
    <file name="boxset_6-u55150-fr.jpg" crc="3869992868" ref="index:boxset"/>
    <file name="hexa - (4)-u55332-fr.png" crc="254811833" ref="index"/>
    <file name="saga - portada-u55509-fr.jpg" crc="3832372604" ref="index:saga"/>
    <file name="u30000-42.png" crc="3863468237" ref="index"/>
    <file name="dsc_0027 copy 2-u44711-fr.jpg" crc="66663102" ref="index"/>
    <file name="boxset_6-u55150-fr2.jpg" crc="3697944" ref="index:boxset"/>
    <file name="hexa - (4)-u55332-fr2.png" crc="4294830561" ref="index"/>
    <file name="saga - portada-u55509-fr2.jpg" crc="160465496" ref="index:saga"/>
    <file name="vaina_presentacion-u55561-fr.jpg" crc="282535153" ref="index:vaina"/>
    <file name="u30000-43.png" crc="3955293184" ref="index"/>
    <file name="menu.png" crc="3935061649" ref="index">
      <caption webpage="index" alt=""/>
      <caption webpage="index" alt=""/>
    </file>
    <file name="cerrado.png" crc="473227605" ref="index">
      <caption webpage="index" alt=""/>
      <caption webpage="index" alt=""/>
    </file>
    <file name="boxset_6-u55150-fr3.jpg" crc="106284828" ref="index"/>
    <file name="saga - portada-u55509-fr3.jpg" crc="271588379" ref="index"/>
    <file name="vaina_presentacion-u55561-fr2.jpg" crc="125118561" ref="index"/>
    <file name="u30000-44.png" crc="4261716533" ref="index"/>
    <file name="u30000-45.png" crc="411244635" ref="index"/>
    <file name="dsc_0027 copy 22.jpg" crc="367827678" ref="mesa-alvaro">
      <caption webpage="mesa-alvaro" alt=""/>
    </file>
    <file name="alvar-aalto-fan-leg.jpg" crc="4261748871" ref="mesa-alvaro">
      <caption webpage="mesa-alvaro" alt=""/>
      <caption webpage="mesa-alvaro" alt=""/>
      <caption webpage="mesa-alvaro" alt=""/>
      <caption webpage="mesa-alvaro" alt=""/>
      <caption webpage="mesa-alvaro" alt=""/>
    </file>
    <file name="sketch.jpg" crc="536644196" ref="mesa-alvaro">
      <caption webpage="mesa-alvaro" alt=""/>
      <caption webpage="mesa-alvaro" alt=""/>
      <caption webpage="mesa-alvaro" alt=""/>
      <caption webpage="mesa-alvaro" alt=""/>
      <caption webpage="mesa-alvaro" alt=""/>
    </file>
    <file name="modelado-3d.jpg" crc="518303712" ref="mesa-alvaro">
      <caption webpage="mesa-alvaro" alt=""/>
      <caption webpage="mesa-alvaro" alt=""/>
      <caption webpage="mesa-alvaro" alt=""/>
      <caption webpage="mesa-alvaro" alt=""/>
      <caption webpage="mesa-alvaro" alt=""/>
    </file>
    <file name="dsc_0026 copy.jpg" crc="3759776800" ref="mesa-alvaro">
      <caption webpage="mesa-alvaro" alt=""/>
    </file>
    <file name="dsc_0036 copy-u47644-fr.jpg" crc="492810611" ref="mesa-alvaro"/>
    <file name="dsc_0146 copy-u47659-fr.jpg" crc="495533498" ref="mesa-alvaro"/>
    <file name="dsc_0106 copy.jpg" crc="4121391686" ref="mesa-alvaro">
      <caption webpage="mesa-alvaro" alt=""/>
    </file>
    <file name="dsc_0036 copy.jpg" crc="4183593285" ref="mesa-alvaro">
      <caption webpage="mesa-alvaro" alt=""/>
    </file>
    <file name="dsc_0146 copy.jpg" crc="517007082" ref="mesa-alvaro">
      <caption webpage="mesa-alvaro" alt=""/>
    </file>
    <file name="dsc_0036 copy-u47644-fr2.jpg" crc="35877354" ref="mesa-alvaro"/>
    <file name="dsc_0146 copy-u47659-fr2.jpg" crc="400317112" ref="mesa-alvaro"/>
    <file name="dsc_0146 copy-u47659-fr3.jpg" crc="300136683" ref="mesa-alvaro"/>
    <file name="dsc_0036 copy-u47644-fr3.jpg" crc="4106842596" ref="mesa-alvaro"/>
    <file name="dsc_0026 copy-u47629-fr.jpg" crc="302233014" ref="mesa-alvaro"/>
    <file name="dsc_0146 copy-u47659-fr4.jpg" crc="17606605" ref="mesa-alvaro"/>
    <file name="dsc_0036 copy-u47644-fr4.jpg" crc="101780969" ref="mesa-alvaro"/>
    <file name="dsc_0106 copy-u48102-fr.jpg" crc="4028032415" ref="mesa-alvaro"/>
    <file name="boxset_2.jpg" crc="132704168" seo="true" ref="boxset">
      <caption webpage="boxset" alt=""/>
      <caption webpage="boxset" alt=""/>
    </file>
    <file name="boxset_1.jpg" crc="4071063575" seo="true" ref="boxset">
      <caption webpage="boxset" alt=""/>
      <caption webpage="boxset" alt=""/>
    </file>
    <file name="boxset_3.jpg" crc="297818001" seo="true" ref="boxset">
      <caption webpage="boxset" alt=""/>
      <caption webpage="boxset" alt=""/>
    </file>
    <file name="boxset_4.jpg" crc="3996087529" seo="true" ref="boxset">
      <caption webpage="boxset" alt=""/>
      <caption webpage="boxset" alt=""/>
    </file>
    <file name="boxset_7.jpg" crc="82297969" seo="true" ref="boxset">
      <caption webpage="boxset" alt=""/>
      <caption webpage="boxset" alt=""/>
    </file>
    <file name="boxset_8.jpg" crc="3892605853" seo="true" ref="boxset">
      <caption webpage="boxset" alt=""/>
      <caption webpage="boxset" alt=""/>
    </file>
    <file name="boxset_5.jpg" crc="466605785" seo="true" ref="boxset">
      <caption webpage="boxset" alt=""/>
      <caption webpage="boxset" alt=""/>
    </file>
    <file name="boxset_9.jpg" crc="3816154944" seo="true" ref="boxset">
      <caption webpage="boxset" alt=""/>
      <caption webpage="boxset" alt=""/>
    </file>
    <file name="boxset_61200x795.jpg" crc="3763551260" seo="true" ref="boxset">
      <caption webpage="boxset" alt=""/>
    </file>
    <file name="boxset_6960x636.jpg" crc="3869992868" seo="true" ref="boxset">
      <caption webpage="boxset" alt=""/>
    </file>
    <file name="boxset_2768x509.jpg" crc="104995661" seo="true" ref="boxset">
      <caption webpage="boxset" alt=""/>
    </file>
    <file name="boxset_1768x481.jpg" crc="4207370217" seo="true" ref="boxset">
      <caption webpage="boxset" alt=""/>
    </file>
    <file name="boxset_3768x509.jpg" crc="22133720" seo="true" ref="boxset">
      <caption webpage="boxset" alt=""/>
    </file>
    <file name="boxset_4768x363.jpg" crc="3893276048" seo="true" ref="boxset">
      <caption webpage="boxset" alt=""/>
    </file>
    <file name="boxset_7768x380.jpg" crc="4246140955" seo="true" ref="boxset">
      <caption webpage="boxset" alt=""/>
    </file>
    <file name="boxset_8768x449.jpg" crc="3861732410" seo="true" ref="boxset">
      <caption webpage="boxset" alt=""/>
    </file>
    <file name="boxset_5768x437.jpg" crc="3977806810" seo="true" ref="boxset">
      <caption webpage="boxset" alt=""/>
    </file>
    <file name="boxset_9768x422.jpg" crc="3839023727" seo="true" ref="boxset">
      <caption webpage="boxset" alt=""/>
    </file>
    <file name="boxset_6768x509.jpg" crc="3697944" seo="true" ref="boxset">
      <caption webpage="boxset" alt=""/>
    </file>
    <file name="boxset_6-u54092-fr.jpg" crc="233173752" ref="boxset"/>
    <file name="boxset_2550x365.jpg" crc="4053460198" seo="true" ref="boxset">
      <caption webpage="boxset" alt=""/>
    </file>
    <file name="boxset_1550x345.jpg" crc="363557181" seo="true" ref="boxset">
      <caption webpage="boxset" alt=""/>
    </file>
    <file name="boxset_3550x365.jpg" crc="240531333" seo="true" ref="boxset">
      <caption webpage="boxset" alt=""/>
    </file>
    <file name="boxset_4550x260.jpg" crc="4289043310" seo="true" ref="boxset">
      <caption webpage="boxset" alt=""/>
    </file>
    <file name="boxset_7550x272.jpg" crc="4019378644" seo="true" ref="boxset">
      <caption webpage="boxset" alt=""/>
    </file>
    <file name="boxset_8550x322.jpg" crc="3790821196" seo="true" ref="boxset">
      <caption webpage="boxset" alt=""/>
    </file>
    <file name="boxset_5550x313.jpg" crc="126141745" seo="true" ref="boxset">
      <caption webpage="boxset" alt=""/>
    </file>
    <file name="boxset_9550x302.jpg" crc="30438188" seo="true" ref="boxset">
      <caption webpage="boxset" alt=""/>
    </file>
    <file name="boxset_6550x365.jpg" crc="42160962" seo="true" ref="boxset">
      <caption webpage="boxset" alt=""/>
    </file>
    <file name="boxset_2320x212.jpg" crc="4252031718" seo="true" ref="boxset">
      <caption webpage="boxset" alt=""/>
    </file>
    <file name="boxset_1320x201.jpg" crc="493225813" seo="true" ref="boxset">
      <caption webpage="boxset" alt=""/>
    </file>
    <file name="boxset_3320x212.jpg" crc="353169905" seo="true" ref="boxset">
      <caption webpage="boxset" alt=""/>
    </file>
    <file name="boxset_4320x152.jpg" crc="491752618" seo="true" ref="boxset">
      <caption webpage="boxset" alt=""/>
    </file>
    <file name="boxset_7320x158.jpg" crc="3902459836" seo="true" ref="boxset">
      <caption webpage="boxset" alt=""/>
    </file>
    <file name="boxset_8320x187.jpg" crc="4188619850" seo="true" ref="boxset">
      <caption webpage="boxset" alt=""/>
    </file>
    <file name="boxset_5320x182.jpg" crc="4187530829" seo="true" ref="boxset">
      <caption webpage="boxset" alt=""/>
    </file>
    <file name="boxset_9320x176.jpg" crc="3929741310" seo="true" ref="boxset">
      <caption webpage="boxset" alt=""/>
    </file>
    <file name="boxset_6320x212.jpg" crc="264500355" seo="true" ref="boxset">
      <caption webpage="boxset" alt=""/>
    </file>
    <file name="hexa - (3)b.png" crc="385729851" ref="hexa">
      <caption webpage="hexa" alt=""/>
    </file>
    <file name="hexa - (2).png" crc="3776362781" seo="true" ref="hexa">
      <caption webpage="hexa" alt=""/>
      <caption webpage="hexa" alt=""/>
      <caption webpage="hexa" alt=""/>
      <caption webpage="hexa" alt=""/>
    </file>
    <file name="hexa - (8).png" crc="3809778676" ref="hexa">
      <caption webpage="hexa" alt=""/>
      <caption webpage="hexa" alt=""/>
    </file>
    <file name="hexa - (4)1200x676.png" crc="4178631993" seo="true" ref="hexa">
      <caption webpage="hexa" alt=""/>
    </file>
    <file name="hexa - (5).png" crc="4156063482" seo="true" ref="hexa">
      <caption webpage="hexa" alt=""/>
      <caption webpage="hexa" alt=""/>
    </file>
    <file name="hexa - (7).png" crc="275066467" seo="true" ref="hexa">
      <caption webpage="hexa" alt=""/>
      <caption webpage="hexa" alt=""/>
    </file>
    <file name="hexa - (1).png" crc="3800485769" seo="true" ref="hexa">
      <caption webpage="hexa" alt=""/>
      <caption webpage="hexa" alt=""/>
    </file>
    <file name="hexa - (6).png" crc="536254238" seo="true" ref="hexa">
      <caption webpage="hexa" alt=""/>
      <caption webpage="hexa" alt=""/>
    </file>
    <file name="hexa---pictogramas.svg" crc="3857118619" seo="true" ref="hexa">
      <caption webpage="hexa" alt=""/>
      <caption webpage="hexa" alt=""/>
      <caption webpage="hexa" alt=""/>
      <caption webpage="hexa" alt=""/>
      <caption webpage="hexa" alt=""/>
    </file>
    <file name="hexa - pictogramas_poster_.png" crc="4242268705" ref="hexa"/>
    <file name="hexa - (3)b1200x413.png" crc="139471795" seo="true" ref="hexa">
      <caption webpage="hexa" alt=""/>
    </file>
    <file name="hexa - comercial-01.jpg" crc="516522380" seo="true" ref="hexa">
      <caption webpage="hexa" alt=""/>
      <caption webpage="hexa" alt=""/>
    </file>
    <file name="hexa - (3)b-u56598-fr.png" crc="317098982" ref="hexa"/>
    <file name="hexa - (4)960x541.png" crc="254811833" seo="true" ref="hexa">
      <caption webpage="hexa" alt=""/>
    </file>
    <file name="hexa - (3)b960x331.png" crc="317098982" seo="true" ref="hexa">
      <caption webpage="hexa" alt=""/>
    </file>
    <file name="hexa - (3)b-u56598-fr2.png" crc="406067535" ref="hexa"/>
    <file name="hexa - (4)768x433.png" crc="213591840" seo="true" ref="hexa">
      <caption webpage="hexa" alt=""/>
    </file>
    <file name="hexa - (5)768x433.png" crc="4031975814" seo="true" ref="hexa">
      <caption webpage="hexa" alt=""/>
    </file>
    <file name="hexa - (7)768x432.png" crc="386825876" seo="true" ref="hexa">
      <caption webpage="hexa" alt=""/>
    </file>
    <file name="hexa - (1)768x433.png" crc="418006389" seo="true" ref="hexa">
      <caption webpage="hexa" alt=""/>
    </file>
    <file name="hexa - (6)768x433.png" crc="4274069427" seo="true" ref="hexa">
      <caption webpage="hexa" alt=""/>
    </file>
    <file name="hexa - (3)b768x265.png" crc="406067535" seo="true" ref="hexa">
      <caption webpage="hexa" alt=""/>
    </file>
    <file name="hexa - comercial-01768x544.jpg" crc="283360849" seo="true" ref="hexa">
      <caption webpage="hexa" alt=""/>
    </file>
    <file name="hexa - (3)b-u56598-fr3.png" crc="381562910" ref="hexa"/>
    <file name="hexa - (4)550x310.png" crc="4235959990" seo="true" ref="hexa">
      <caption webpage="hexa" alt=""/>
    </file>
    <file name="hexa - (5)550x310.png" crc="415987619" seo="true" ref="hexa">
      <caption webpage="hexa" alt=""/>
    </file>
    <file name="hexa - (7)550x310.png" crc="223000040" seo="true" ref="hexa">
      <caption webpage="hexa" alt=""/>
    </file>
    <file name="hexa - (1)550x310.png" crc="219550993" seo="true" ref="hexa">
      <caption webpage="hexa" alt=""/>
    </file>
    <file name="hexa - (6)550x310.png" crc="4020872290" seo="true" ref="hexa">
      <caption webpage="hexa" alt=""/>
    </file>
    <file name="hexa - (3)b550x190.png" crc="3898709708" seo="true" ref="hexa">
      <caption webpage="hexa" alt=""/>
    </file>
    <file name="hexa - comercial-01550x389.jpg" crc="33003019" seo="true" ref="hexa">
      <caption webpage="hexa" alt=""/>
    </file>
    <file name="hexa - (3)b-u56598-fr4.png" crc="366440758" ref="hexa"/>
    <file name="hexa - (2)320x453.png" crc="4040212328" seo="true" ref="hexa">
      <caption webpage="hexa" alt=""/>
    </file>
    <file name="hexa - (8)-u57973-fr.png" crc="28009387" ref="hexa"/>
    <file name="hexa - (4)320x181.png" crc="4218250712" seo="true" ref="hexa">
      <caption webpage="hexa" alt=""/>
    </file>
    <file name="hexa - (5)320x181.png" crc="4252344154" seo="true" ref="hexa">
      <caption webpage="hexa" alt=""/>
    </file>
    <file name="hexa - (7)320x180.png" crc="3760836245" seo="true" ref="hexa">
      <caption webpage="hexa" alt=""/>
    </file>
    <file name="hexa - (1)320x180.png" crc="407214438" seo="true" ref="hexa">
      <caption webpage="hexa" alt=""/>
    </file>
    <file name="hexa - (6)320x180.png" crc="235493639" seo="true" ref="hexa">
      <caption webpage="hexa" alt=""/>
    </file>
    <file name="hexa - (3)b320x110.png" crc="16258620" seo="true" ref="hexa">
      <caption webpage="hexa" alt=""/>
    </file>
    <file name="hexa - comercial-01320x227.jpg" crc="3953206394" seo="true" ref="hexa">
      <caption webpage="hexa" alt=""/>
    </file>
    <file name="saga - principal.jpg" crc="3943010031" seo="true" ref="saga">
      <caption webpage="saga" alt=""/>
      <caption webpage="saga" alt=""/>
    </file>
    <file name="saga (2).png" crc="4034655440" seo="true" ref="saga">
      <caption webpage="saga" alt=""/>
      <caption webpage="saga" alt=""/>
    </file>
    <file name="saga (5).png" crc="7981183" seo="true" ref="saga">
      <caption webpage="saga" alt=""/>
      <caption webpage="saga" alt=""/>
    </file>
    <file name="saga (1).png" crc="365686530" seo="true" ref="saga">
      <caption webpage="saga" alt=""/>
      <caption webpage="saga" alt=""/>
    </file>
    <file name="saga (3).png" crc="3921921936" seo="true" ref="saga">
      <caption webpage="saga" alt=""/>
      <caption webpage="saga" alt=""/>
    </file>
    <file name="saga (4).png" crc="335393859" seo="true" ref="saga">
      <caption webpage="saga" alt=""/>
      <caption webpage="saga" alt=""/>
    </file>
    <file name="saga (3).jpg" crc="310990268" seo="true" ref="saga">
      <caption webpage="saga" alt=""/>
      <caption webpage="saga" alt=""/>
    </file>
    <file name="saga (6).jpg" crc="298199564" seo="true" ref="saga">
      <caption webpage="saga" alt=""/>
      <caption webpage="saga" alt=""/>
    </file>
    <file name="saga (8).jpg" crc="427029916" seo="true" ref="saga">
      <caption webpage="saga" alt=""/>
      <caption webpage="saga" alt=""/>
    </file>
    <file name="saga - detalle 1.jpg" crc="3940171198" seo="true" ref="saga">
      <caption webpage="saga" alt=""/>
      <caption webpage="saga" alt=""/>
    </file>
    <file name="saga (4).jpg" crc="298702468" seo="true" ref="saga">
      <caption webpage="saga" alt=""/>
      <caption webpage="saga" alt=""/>
    </file>
    <file name="saga - principal768x843.jpg" crc="4010390647" seo="true" ref="saga">
      <caption webpage="saga" alt=""/>
    </file>
    <file name="saga (2)768x1060.png" crc="4239746195" seo="true" ref="saga">
      <caption webpage="saga" alt=""/>
    </file>
    <file name="saga (5)768x948.png" crc="3922283323" seo="true" ref="saga">
      <caption webpage="saga" alt=""/>
    </file>
    <file name="saga (1)768x433.png" crc="245713497" seo="true" ref="saga">
      <caption webpage="saga" alt=""/>
    </file>
    <file name="saga (3)386x728.png" crc="106382187" seo="true" ref="saga">
      <caption webpage="saga" alt=""/>
    </file>
    <file name="saga (4)383x730.png" crc="260265139" seo="true" ref="saga">
      <caption webpage="saga" alt=""/>
    </file>
    <file name="saga (3)768x405.jpg" crc="330429145" seo="true" ref="saga">
      <caption webpage="saga" alt=""/>
    </file>
    <file name="saga (6)768x509.jpg" crc="316735464" seo="true" ref="saga">
      <caption webpage="saga" alt=""/>
    </file>
    <file name="saga (8)768x509.jpg" crc="103202647" seo="true" ref="saga">
      <caption webpage="saga" alt=""/>
    </file>
    <file name="saga - detalle 1768x507.jpg" crc="406543328" seo="true" ref="saga">
      <caption webpage="saga" alt=""/>
    </file>
    <file name="saga (4)768x684.jpg" crc="4141801269" seo="true" ref="saga">
      <caption webpage="saga" alt=""/>
    </file>
    <file name="saga - portada-u56947-fr.jpg" crc="4121249266" ref="saga"/>
    <file name="saga - principal551x604.jpg" crc="4227084635" seo="true" ref="saga">
      <caption webpage="saga" alt=""/>
    </file>
    <file name="saga (2)551x760.png" crc="3878427132" seo="true" ref="saga">
      <caption webpage="saga" alt=""/>
    </file>
    <file name="saga (5)551x679.png" crc="3759856101" seo="true" ref="saga">
      <caption webpage="saga" alt=""/>
    </file>
    <file name="saga (1)551x310.png" crc="412272948" seo="true" ref="saga">
      <caption webpage="saga" alt=""/>
    </file>
    <file name="saga (3)277x522.png" crc="273437901" seo="true" ref="saga">
      <caption webpage="saga" alt=""/>
    </file>
    <file name="saga (4)274x523.png" crc="235226546" seo="true" ref="saga">
      <caption webpage="saga" alt=""/>
    </file>
    <file name="saga (3)551x290.jpg" crc="4256439083" seo="true" ref="saga">
      <caption webpage="saga" alt=""/>
    </file>
    <file name="saga (6)551x365.jpg" crc="120783371" seo="true" ref="saga">
      <caption webpage="saga" alt=""/>
    </file>
    <file name="saga (8)551x365.jpg" crc="241515922" seo="true" ref="saga">
      <caption webpage="saga" alt=""/>
    </file>
    <file name="saga - detalle 1550x363.jpg" crc="259576051" seo="true" ref="saga">
      <caption webpage="saga" alt=""/>
    </file>
    <file name="saga (4)550x490.jpg" crc="145876627" seo="true" ref="saga">
      <caption webpage="saga" alt=""/>
    </file>
    <file name="saga - portada-u56947-fr2.jpg" crc="4206916758" ref="saga"/>
    <file name="saga - principal321x352.jpg" crc="4050199995" seo="true" ref="saga">
      <caption webpage="saga" alt=""/>
    </file>
    <file name="saga (2)321x442.png" crc="4275527940" seo="true" ref="saga">
      <caption webpage="saga" alt=""/>
    </file>
    <file name="saga (5)321x395.png" crc="244858126" seo="true" ref="saga">
      <caption webpage="saga" alt=""/>
    </file>
    <file name="saga (1)321x181.png" crc="4086680573" seo="true" ref="saga">
      <caption webpage="saga" alt=""/>
    </file>
    <file name="saga (3)161x304.png" crc="353829953" seo="true" ref="saga">
      <caption webpage="saga" alt=""/>
    </file>
    <file name="saga (4)160x304.png" crc="36200484" seo="true" ref="saga">
      <caption webpage="saga" alt=""/>
    </file>
    <file name="saga (3)321x169.jpg" crc="4151049638" seo="true" ref="saga">
      <caption webpage="saga" alt=""/>
    </file>
    <file name="saga (6)321x212.jpg" crc="137318633" seo="true" ref="saga">
      <caption webpage="saga" alt=""/>
    </file>
    <file name="saga (8)321x212.jpg" crc="154842549" seo="true" ref="saga">
      <caption webpage="saga" alt=""/>
    </file>
    <file name="saga - detalle 1320x211.jpg" crc="5319528" seo="true" ref="saga">
      <caption webpage="saga" alt=""/>
    </file>
    <file name="saga (4)320x285.jpg" crc="3925754869" seo="true" ref="saga">
      <caption webpage="saga" alt=""/>
    </file>
    <file name="vaina_edit.jpg" crc="3781567452" seo="true" ref="vaina">
      <caption webpage="vaina" alt=""/>
      <caption webpage="vaina" alt=""/>
    </file>
    <file name="vaina (3).jpg" crc="23878730" seo="true" ref="vaina">
      <caption webpage="vaina" alt=""/>
      <caption webpage="vaina" alt=""/>
    </file>
    <file name="vaina (4).jpg" crc="402995784" seo="true" ref="vaina">
      <caption webpage="vaina" alt=""/>
      <caption webpage="vaina" alt=""/>
    </file>
    <file name="vaina jarra.jpg" crc="3765261519" seo="true" ref="vaina">
      <caption webpage="vaina" alt=""/>
      <caption webpage="vaina" alt=""/>
    </file>
    <file name="vaina (2).jpg" crc="4102378951" seo="true" ref="vaina">
      <caption webpage="vaina" alt=""/>
      <caption webpage="vaina" alt=""/>
    </file>
    <file name="vaina kit.jpg" crc="422942182" seo="true" ref="vaina">
      <caption webpage="vaina" alt=""/>
      <caption webpage="vaina" alt=""/>
    </file>
    <file name="vaina (1).jpg" crc="3917075148" seo="true" ref="vaina">
      <caption webpage="vaina" alt=""/>
      <caption webpage="vaina" alt=""/>
    </file>
    <file name="vaina_edit780x491.jpg" crc="522473295" seo="true" ref="vaina">
      <caption webpage="vaina" alt=""/>
    </file>
    <file name="vaina (3)780x516.jpg" crc="3880728777" seo="true" ref="vaina">
      <caption webpage="vaina" alt=""/>
    </file>
    <file name="vaina (4)780x516.jpg" crc="406006857" seo="true" ref="vaina">
      <caption webpage="vaina" alt=""/>
    </file>
    <file name="vaina jarra780x516.jpg" crc="413004330" seo="true" ref="vaina">
      <caption webpage="vaina" alt=""/>
    </file>
    <file name="vaina (2)780x516.jpg" crc="464142395" seo="true" ref="vaina">
      <caption webpage="vaina" alt=""/>
    </file>
    <file name="vaina kit780x516.jpg" crc="3833147879" seo="true" ref="vaina">
      <caption webpage="vaina" alt=""/>
    </file>
    <file name="vaina (1)780x519.jpg" crc="172335753" seo="true" ref="vaina">
      <caption webpage="vaina" alt=""/>
    </file>
    <file name="vaina_presentacion-u57123-fr.jpg" crc="501020152" ref="vaina"/>
    <file name="vaina_edit555x350.jpg" crc="4027325453" seo="true" ref="vaina">
      <caption webpage="vaina" alt=""/>
    </file>
    <file name="vaina (3)555x368.jpg" crc="115942556" seo="true" ref="vaina">
      <caption webpage="vaina" alt=""/>
    </file>
    <file name="vaina (4)555x368.jpg" crc="288791274" seo="true" ref="vaina">
      <caption webpage="vaina" alt=""/>
    </file>
    <file name="vaina jarra555x368.jpg" crc="3909969528" seo="true" ref="vaina">
      <caption webpage="vaina" alt=""/>
    </file>
    <file name="vaina (2)555x368.jpg" crc="3991866353" seo="true" ref="vaina">
      <caption webpage="vaina" alt=""/>
    </file>
    <file name="vaina kit555x368.jpg" crc="248258756" seo="true" ref="vaina">
      <caption webpage="vaina" alt=""/>
    </file>
    <file name="vaina (1)555x370.jpg" crc="4162861292" seo="true" ref="vaina">
      <caption webpage="vaina" alt=""/>
    </file>
    <file name="vaina_presentacion-u57123-fr2.jpg" crc="355239015" ref="vaina"/>
    <file name="vaina_edit320x202.jpg" crc="40520285" seo="true" ref="vaina">
      <caption webpage="vaina" alt=""/>
    </file>
    <file name="vaina (3)320x212.jpg" crc="4244393260" seo="true" ref="vaina">
      <caption webpage="vaina" alt=""/>
    </file>
    <file name="vaina (4)320x212.jpg" crc="4124979887" seo="true" ref="vaina">
      <caption webpage="vaina" alt=""/>
    </file>
    <file name="vaina jarra320x212.jpg" crc="415035177" seo="true" ref="vaina">
      <caption webpage="vaina" alt=""/>
    </file>
    <file name="vaina (2)320x212.jpg" crc="3875682256" seo="true" ref="vaina">
      <caption webpage="vaina" alt=""/>
    </file>
    <file name="vaina kit320x212.jpg" crc="38167277" seo="true" ref="vaina">
      <caption webpage="vaina" alt=""/>
    </file>
    <file name="vaina (1)320x213.jpg" crc="231845889" seo="true" ref="vaina">
      <caption webpage="vaina" alt=""/>
    </file>
  </folder>
  <file name="index.html" crc="416996170" seo="true" mt="1526949134757" redirect="true"/>
  <file name="mesa-alvaro.html" crc="334887408" seo="true" mt="1524160216364" redirect="true"/>
  <file name="boxset.html" crc="39093504" seo="true" mt="1526946325428" redirect="true"/>
  <file name="hexa.html" crc="201494396" seo="true" mt="1526946049794" redirect="true"/>
  <file name="saga.html" crc="4165678074" seo="true" mt="1526949134755" redirect="true"/>
  <file name="vaina.html" crc="4129538308" seo="true" mt="1526950132119" redirect="true"/>
</manifest>